README.txt
setup.cfg
setup.py
archetypes/__init__.py
archetypes.memberdatastorage.egg-info/PKG-INFO
archetypes.memberdatastorage.egg-info/SOURCES.txt
archetypes.memberdatastorage.egg-info/dependency_links.txt
archetypes.memberdatastorage.egg-info/entry_points.txt
archetypes.memberdatastorage.egg-info/namespace_packages.txt
archetypes.memberdatastorage.egg-info/not-zip-safe
archetypes.memberdatastorage.egg-info/requires.txt
archetypes.memberdatastorage.egg-info/top_level.txt
archetypes/memberdatastorage/__init__.py
archetypes/memberdatastorage/memberdatastorage.py
archetypes/memberdatastorage/memberpropertyfield.py
archetypes/memberdatastorage/tests/__init__.py
archetypes/memberdatastorage/tests/test_memberpropertyfield.py
docs/HISTORY.txt