Metadata-Version: 1.0
Name: archetypes.memberdatastorage
Version: 1.1
Summary: A facade storage layer for Archetypes delegating to the Plone memberdata tool
Home-page: http://plone.org/products/archetypes.memberdatastorage
Author: Raphael Ritz
Author-email: raphael.ritz@incf.org
License: BSD
Keywords: Plone Archetypes Storage Memberdata
Platform: UNKNOWN
Classifier: Programming Language :: Python
Classifier: Topic :: Software Development :: Libraries :: Python Modules
